Metadata-Version: 2.1
Name: django-exc
Version: 2020.7.3
Summary: Django exceptions tracker
Home-page: https://github.com/andrewp-as-is/django-exc.py
License: Unlicense
Keywords: django exception
Platform: UNKNOWN
Classifier: Framework :: Django
Classifier: License :: Public Domain
Classifier: Operating System :: OS Independent
Classifier: Programming Language :: Python :: 3
